raybender/scene.py
raybender/utils.py
raybender/_raybender.cp314t-win_amd64.pyd
raybender/__init__.py
raybender-4.0.3.dist-info/DELVEWHEEL
raybender-4.0.3.dist-info/METADATA
raybender-4.0.3.dist-info/RECORD
raybender-4.0.3.dist-info/top_level.txt
raybender-4.0.3.dist-info/WHEEL
raybender-4.0.3.dist-info/licenses/LICENSE
raybender.libs/embree4.dll
raybender.libs/msvcp140-a4c2229bdc2a2a630acdc095b4d86008.dll
raybender.libs/tbb12.dll
