Metadata-Version: 2.4
Name: raybender
Version: 4.0.3
Summary: Embree bindings for Python
Author-email: Mihai Dusmanu <mihai.dusmanu@inf.ethz.ch>
License: BSD 3-Clause License
Project-URL: Homepage, https://github.com/cvg/raybender
Requires-Python: >=3.9
License-File: LICENSE
Requires-Dist: numpy
Provides-Extra: test
Requires-Dist: pytest; extra == "test"
Requires-Dist: trimesh; extra == "test"
Requires-Dist: scipy; extra == "test"
Requires-Dist: pillow; extra == "test"
Dynamic: license-file
